xraptor/__init__.py
xraptor/antenna_implementations/__init__.py
xraptor/antenna_implementations/memory.py
xraptor/antenna_implementations/redis.py
xraptor/broadcaster.py
xraptor/connection.py
xraptor/core/__init__.py
xraptor/core/interfaces.py
xraptor/domain/__init__.py
xraptor/domain/methods.py
xraptor/domain/request.py
xraptor/domain/response.py
xraptor/domain/route.py
xraptor/server.py
xraptor-0.3.5.dist-info/METADATA
xraptor-0.3.5.dist-info/WHEEL
xraptor-0.3.5.dist-info/licenses/LICENSE
xraptor-0.3.5.dist-info/RECORD
