Metadata-Version: 2.4
Name: xraptor
Version: 0.3.5
Summary: Fast as websocket easy as http
License-File: LICENSE
Author: Marco Sievers de Almeida
Author-email: im.ximit@gmail.com
Requires-Python: >=3.11,<4.0
Classifier: Programming Language :: Python :: 3
Classifier: Programming Language :: Python :: 3.11
Classifier: Programming Language :: Python :: 3.12
Classifier: Programming Language :: Python :: 3.13
Classifier: Programming Language :: Python :: 3.14
Provides-Extra: redis-version
Requires-Dist: meeseeks-singleton (>=0.4.4,<0.5.0)
Requires-Dist: python-decouple (>=3.8,<4.0)
Requires-Dist: python-ulid (>=2.7.0,<3.0.0)
Requires-Dist: redis (>=5.0.8,<6.0.0) ; extra == "redis-version"
Requires-Dist: websockets (>=12.0,<13.0)
Requires-Dist: witch-doctor (>=1.2.0,<2.0.0)
Project-URL: documentation, https://github.com/CenturyBoys/x-raptor
Project-URL: homepage, https://github.com/CenturyBoys/x-raptor
Project-URL: repository, https://github.com/CenturyBoys/x-raptor
